Password_Safe_Box/Help.py
Password_Safe_Box/Password_Fastest.py
Password_Safe_Box/Password_Most_Secured.py
Password_Safe_Box/__init__.py
Password_Safe_Box-0.2.dist-info/LICENSE.txt
Password_Safe_Box-0.2.dist-info/METADATA
Password_Safe_Box-0.2.dist-info/WHEEL
Password_Safe_Box-0.2.dist-info/top_level.txt
Password_Safe_Box-0.2.dist-info/RECORD
