Metadata-Version: 2.1
Name: Password-Safe-Box
Version: 0.2
Summary: Store any password you want with the most secure way
Home-page: https://github.com/Vbrawl/Password_Safe_Box
Author: Jim
Author-email: TheDarkProgrammers@gmail.com
License: UNKNOWN
Platform: UNKNOWN
Classifier: Development Status :: 4 - Beta
Classifier: License :: OSI Approved :: MIT License
Classifier: Programming Language :: Python :: 3
Classifier: Operating System :: OS Independent
Requires-Python: >=3.x
